Workbook

Sheet Chart of Accounts ERPNext
A1: BAGAN AKUN (CHART OF ACCOUNTS) INDUSTRI MANUFAKTUR - ERPNEXT
A2: Format Standar Siap Import ke ERPNext (Accounting > Chart of Accounts Importer / Data Import)
A4: Account Code (Kode Akun) | B4: Account Name (Nama Akun) | C4: Parent Account Code (Kode Induk) | D4: Parent Account Name (Nama Akun Induk) | E4: Root Type (Kategori Utama) | F4: Is Group (1=Induk, 0=Transaksi) | G4: Account Type (Tipe Akun ERPNext) | H4: Kategori Manufaktur (Fungsi Operasional) | I4: Keterangan / Fungsi Akun
A5: 1000 | B5: ASET | E5: Asset | F5: 1 | H5: Header Utama | I5: Induk utama seluruh aset perusahaan manufaktur
A6: 1100 | B6: Aset Lancar | C6: 1000 | D6: ASET | E6: Asset | F6: 1 | H6: Aset Lancar | I6: Kelompok aset cair dan operasional jangka pendek (<1 tahun)
A7: 1110 | B7: Kas & Bank | C7: 1100 | D7: Aset Lancar | E7: Asset | F7: 1 | G7: Bank | H7: Kas & Bank | I7: Kelompok seluruh rekening kas tunai dan bank
A8: 1111 | B8: Kas Utama Pabrik | C8: 1110 | D8: Kas & Bank | E8: Asset | F8: 0 | G8: Cash | H8: Kas & Bank | I8: Kas tunai untuk operasional harian pabrik
A9: 1112 | B9: Kas Kecil (Petty Cash) | C9: 1110 | D9: Kas & Bank | E9: Asset | F9: 0 | G9: Cash | H9: Kas & Bank | I9: Kas kecil pengeluaran operasional darurat
A10: 1113 | B10: Bank Mandiri Operasional | C10: 1110 | D10: Kas & Bank | E10: Asset | F10: 0 | G10: Bank | H10: Kas & Bank | I10: Rekening penerimaan pelanggan & pembayaran vendor
A11: 1114 | B11: Bank BCA Operasional | C11: 1110 | D11: Kas & Bank | E11: Asset | F11: 0 | G11: Bank | H11: Kas & Bank | I11: Rekening penggajian (payroll) & utilitas pabrik
A12: 1120 | B12: Piutang Usaha & Lainnya | C12: 1100 | D12: Aset Lancar | E12: Asset | F12: 1 | G12: Receivable | H12: Piutang | I12: Kelompok piutang pelanggan dan karyawan
A13: 1121 | B13: Piutang Usaha (Dagang) | C13: 1120 | D13: Piutang Usaha & Lainnya | E13: Asset | F13: 0 | G13: Receivable | H13: Piutang | I13: Terikat otomatis ke Sales Invoice Pelanggan (Customer)
A14: 1122 | B14: Cadangan Kerugian Piutang | C14: 1120 | D14: Piutang Usaha & Lainnya | E14: Asset | F14: 0 | G14: Receivable | H14: Piutang | I14: Akun kontra piutang tak tertagih
A15: 1123 | B15: Piutang Karyawan & Kasbon | C15: 1120 | D15: Piutang Usaha & Lainnya | E15: Asset | F15: 0 | G15: Receivable | H15: Piutang | I15: Pinjaman/kasbon sementara staf & buruh pabrik
A16: 1130 | B16: Persediaan (Stock) | C16: 1100 | D16: Aset Lancar | E16: Asset | F16: 1 | G16: Stock | H16: Persediaan Manufaktur | I16: Kelompok persediaan bahan & barang manufaktur
A17: 1131 | B17: Persediaan Bahan Baku (Raw Materials) | C17: 1130 | D17: Persediaan (Stock) | E17: Asset | F17: 0 | G17: Stock | H17: Bahan Baku | I17: Nilai fisik bahan baku utama produksi
A18: 1132 | B18: Persediaan Bahan Penolong (Auxiliary Materials) | C18: 1130 | D18: Persediaan (Stock) | E18: Asset | F18: 0 | G18: Stock | H18: Bahan Penolong | I18: Nilai bahan pelengkap/kimia/perekat produksi
... A23: 1137 | B23: Barang Dalam Perjalanan (Stock In Transit) | C23: 1130 | D23: Persediaan (Stock) | E23: Asset | F23: 0 | G23: Stock | H23: Stock In Transit | I23: Stok bahan baku/barang yang sedang dalam pengiriman
A24: 1140 | B24: Uang Muka & Biaya Dibayar Muka | C24: 1100 | D24: Aset Lancar | E24: Asset | F24: 1 | H24: Uang Muka | I24: Pembayaran di awal untuk vendor/sewa/pajak
A25: 1141 | B25: Uang Muka Pembelian Bahan Baku | C25: 1140 | D25: Uang Muka & Biaya Dibayar Muka | E25: Asset | F25: 0 | G25: Payable | H25: Uang Muka Vendor | I25: DP/Uang muka pembelian ke supplier bahan baku
A26: 1142 | B26: Uang Muka Sewa Gedung Pabrik | C26: 1140 | D26: Uang Muka & Biaya Dibayar Muka | E26: Asset | F26: 0 | H26: Uang Muka Sewa | I26: Sewa gedung/lahan pabrik dibayar di muka
A27: 1143 | B27: Uang Muka Asuransi Mesin & Pabrik | C27: 1140 | D27: Uang Muka & Biaya Dibayar Muka | E27: Asset | F27: 0 | H27: Uang Muka Asuransi | I27: Asuransi kebakaran/mesin dibayar di muka
A28: 1144 | B28: PPN Masukan (Input VAT) | C28: 1140 | D28: Uang Muka & Biaya Dibayar Muka | E28: Asset | F28: 0 | G28: Tax | H28: Pajak Masukan | I28: PPN 11% atas pembelian bahan baku & jasa
A29: 1200 | B29: Aset Tetap (Fixed Assets) | C29: 1000 | D29: ASET | E29: Asset | F29: 1 | G29: Fixed Asset | H29: Aset Tetap | I29: Induk seluruh aset tetap pabrik & kantor
A30: 1210 | B30: Tanah & Bangunan Pabrik | C30: 1200 | D30: Aset Tetap (Fixed Assets) | E30: Asset | F30: 1 | G30: Fixed Asset | H30: Infrastruktur Pabrik | I30: Infrastruktur tanah & gedung pabrik
A31: 1211 | B31: Tanah Pabrik | C31: 1210 | D31: Tanah & Bangunan Pabrik | E31: Asset | F31: 0 | G31: Fixed Asset | H31: Infrastruktur Pabrik | I31: Nilai perolehan tanah pabrik & pergudangan
A32: 1212 | B32: Bangunan & Gedung Pabrik | C32: 1210 | D32: Tanah & Bangunan Pabrik | E32: Asset | F32: 0 | G32: Fixed Asset | H32: Infrastruktur Pabrik | I32: Nilai perolehan gedung pabrik & gudang
A33: 1213 | B33: Akum. Penyusutan Bangunan Pabrik | C33: 1210 | D33: Tanah & Bangunan Pabrik | E33: Asset | F33: 0 | G33: Accumulated Depreciation | H33: Penyusutan | I33: Akumulasi depresiasi gedung pabrik (kontra aset)
A34: 1220 | B34: Mesin & Peralatan Produksi | C34: 1200 | D34: Aset Tetap (Fixed Assets) | E34: Asset | F34: 1 | G34: Fixed Asset | H34: Mesin Produksi | I34: Seluruh lini mesin produksi manufaktur
A35: 1221 | B35: Mesin Produksi & Lini Perakitan | C35: 1220 | D35: Mesin & Peralatan Produksi | E35: Asset | F35: 0 | G35: Fixed Asset | H35: Mesin Produksi | I35: Nilai perolehan mesin CNC, cetak, potong, dll.
A36: 1222 | B36: Akum. Penyusutan Mesin Produksi | C36: 1220 | D36: Mesin & Peralatan Produksi | E36: Asset | F36: 0 | G36: Accumulated Depreciation | H36: Penyusutan | I36: Akumulasi depresiasi mesin pabrik
A37: 1223 | B37: Alat Berat & Forklift Pabrik | C37: 1220 | D37: Mesin & Peralatan Produksi | E37: Asset | F37: 0 | G37: Fixed Asset | H37: Alat Berat Pabrik | I37: Nilai perolehan forklift, loader, crane pabrik
A38: 1224 | B38: Akum. Penyusutan Alat Berat | C38: 1220 | D38: Mesin & Peralatan Produksi | E38: Asset | F38: 0 | G38: Accumulated Depreciation | H38: Penyusutan | I38: Akumulasi depresiasi alat berat pabrik
A39: 1230 | B39: Inventaris & IT Kantor | C39: 1200 | D39: Aset Tetap (Fixed Assets) | E39: Asset | F39: 1 | G39: Fixed Asset | H39: Aset Kantor | I39: Peralatan pendukung kantor & sistem IT
... A41: 1232 | B41: Akum. Penyusutan Peralatan Kantor | C41: 1230 | D41: Inventaris & IT Kantor | E41: Asset | F41: 0 | G41: Accumulated Depreciation | H41: Penyusutan | I41: Akumulasi depresiasi peralatan kantor
A42: 2000 | B42: KEWAJIBAN (LIABILITAS) | E42: Liability | F42: 1 | H42: Header Utama | I42: Induk utama seluruh hutang & kewajiban
A43: 2100 | B43: Kewajiban Jangka Pendek | C43: 2000 | D43: KEWAJIBAN (LIABILITAS) | E43: Liability | F43: 1 | H43: Hutang Lancar | I43: Kewajiban yang harus dilunasi dalam <1 tahun
A44: 2110 | B44: Hutang Usaha & Pengadaan | C44: 2100 | D44: Kewajiban Jangka Pendek | E44: Liability | F44: 1 | G44: Payable | H44: Hutang Usaha | I44: Kelompok hutang ke supplier & subkontraktor
A45: 2111 | B45: Hutang Dagang (Pemasok Bahan Baku) | C45: 2110 | D45: Hutang Usaha & Pengadaan | E45: Liability | F45: 0 | G45: Payable | H45: Hutang Bahan Baku | I45: Terikat otomatis ke Purchase Invoice Supplier
A46: 2112 | B46: Hutang Jasa Makloon (Subkontrak) | C46: 2110 | D46: Hutang Usaha & Pengadaan | E46: Liability | F46: 0 | G46: Payable | H46: Hutang Makloon | I46: Hutang atas pekerjaan produksi yang di-subkontrakkan
A47: 2113 | B47: Uang Muka Penjualan (Customer Advance) | C47: 2110 | D47: Hutang Usaha & Pengadaan | E47: Liability | F47: 0 | G47: Receivable | H47: Uang Muka Pelanggan | I47: DP/Uang muka dari customer atas pesanan barang
A48: 2120 | B48: Beban Akrual & Masih Harus Dibayar | C48: 2100 | D48: Kewajiban Jangka Pendek | E48: Liability | F48: 1 | H48: Beban Akrual | I48: Akrual gaji, utilitas, dan kewajiban harian
A49: 2121 | B49: Hutang Gaji & Upah Buruh Pabrik | C49: 2120 | D49: Beban Akrual & Masih Harus Dibayar | E49: Liability | F49: 0 | G49: Payable | H49: Akrual Gaji | I49: Gaji buruh & staf pabrik yang belum dicairkan
A50: 2122 | B50: Hutang Listrik, Air & Utilitas Pabrik | C50: 2120 | D50: Beban Akrual & Masih Harus Dibayar | E50: Liability | F50: 0 | H50: Akrual Utilitas | I50: Tagihan PLN industri/utilitas bulan berjalan
A51: 2123 | B51: Hutang BPJS Ketenagakerjaan & Kesehatan | C51: 2120 | D51: Beban Akrual & Masih Harus Dibayar | E51: Liability | F51: 0 | H51: Akrual BPJS | I51: Iuran BPJS buruh & staf pabrik
A52: 2130 | B52: Kewajiban Perpajakan | C52: 2100 | D52: Kewajiban Jangka Pendek | E52: Liability | F52: 1 | G52: Tax | H52: Pajak | I52: Seluruh kewajiban pajak ke kas negara
A53: 2131 | B53: PPN Keluaran (Output VAT) | C53: 2130 | D53: Kewajiban Perpajakan | E53: Liability | F53: 0 | G53: Tax | H53: Pajak Keluaran | I53: PPN 11% yang dipungut dari hasil penjualan barang
A54: 2132 | B54: Hutang PPh 21 (Gaji & Buruh) | C54: 2130 | D54: Kewajiban Perpajakan | E54: Liability | F54: 0 | G54: Tax | H54: Pajak Karyawan | I54: Potongan PPh 21 atas gaji staf & upah buruh
A55: 2133 | B55: Hutang PPh 22 (Impor Bahan Baku) | C55: 2130 | D55: Kewajiban Perpajakan | E55: Liability | F55: 0 | G55: Tax | H55: Pajak Impor | I55: PPh 22 atas impor bahan baku/peralatan
A56: 2134 | B56: Hutang PPh 23 (Makloon & Sewa) | C56: 2130 | D56: Kewajiban Perpajakan | E56: Liability | F56: 0 | G56: Tax | H56: Pajak Jasa | I56: Potongan PPh 23 atas jasa makloon/sewa alat
A57: 2135 | B57: Hutang PPh Pasal 25/29 Badan | C57: 2130 | D57: Kewajiban Perpajakan | E57: Liability | F57: 0 | G57: Tax | H57: Pajak Badan | I57: Angsuran/kurang bayar PPh Badan Tahunan
A58: 2200 | B58: Kewajiban Jangka Panjang | C58: 2000 | D58: KEWAJIBAN (LIABILITAS) | E58: Liability | F58: 1 | H58: Hutang Jangka Panjang | I58: Pinjaman jangka panjang (>1 tahun)
A59: 2210 | B59: Hutang Bank & Leasing Mesin | C59: 2200 | D59: Kewajiban Jangka Panjang | E59: Liability | F59: 0 | H59: Pinjaman Modal | I59: Kredit investasi mesin, pabrik, dan leasing alat
A60: 3000 | B60: EKUITAS (MODAL) | E60: Equity | F60: 1 | H60: Header Utama | I60: Induk utama modal & ekuitas pemilik
A61: 3100 | B61: Modal Perusahaan & Cadangan | C61: 3000 | D61: EKUITAS (MODAL) | E61: Equity | F61: 1 | G61: Equity | H61: Modal | I61: Kelompok modal disetor & saldo laba
A62: 3110 | B62: Modal Disetor | C62: 3100 | D62: Modal Perusahaan & Cadangan | E62: Equity | F62: 0 | G62: Equity | H62: Modal Disetor | I62: Setoran modal saham awal pemilik perusahaan
A63: 3120 | B63: Laba Ditahan (Retained Earnings) | C63: 3100 | D63: Modal Perusahaan & Cadangan | E63: Equity | F63: 0 | G63: Equity | H63: Laba Ditahan | I63: Akumulasi laba bersih tahun-tahun sebelumnya
A64: 3130 | B64: Laba Tahun Berjalan | C64: 3100 | D64: Modal Perusahaan & Cadangan | E64: Equity | F64: 0 | G64: Equity | H64: Laba Berjalan | I64: Penampung otomatis laba/rugi periode berjalan
A65: 3140 | B65: Akun Penyeimbang Stok (Stock Adjustment Clearing) | C65: 3100 | D65: Modal Perusahaan & Cadangan | E65: Equity | F65: 0 | G65: Stock | H65: Clearing Stok | I65: Penyeimbang selisih nilai fisik & sistem persediaan
A66: 4000 | B66: PENDAPATAN | E66: Income | F66: 1 | H66: Header Utama | I66: Induk utama hasil penjualan & pendapatan
A67: 4100 | B67: Pendapatan Operasional Utama | C67: 4000 | D67: PENDAPATAN | E67: Income | F67: 1 | G67: Income Account | H67: Penjualan Utama | I67: Hasil penjualan produk manufaktur
A68: 4110 | B68: Penjualan Barang Jadi (Finished Goods Sales) | C68: 4100 | D68: Pendapatan Operasional Utama | E68: Income | F68: 0 | G68: Income Account | H68: Penjualan Produk | I68: Otomatis terhubung ke Sales Invoice Penjualan Barang
A69: 4120 | B69: Pendapatan Jasa Makloon (Subcontracting) | C69: 4100 | D69: Pendapatan Operasional Utama | E69: Income | F69: 0 | G69: Income Account | H69: Penjualan Jasa Makloon | I69: Pendapatan dari pemrosesan barang milik pihak ke-3
A70: 4130 | B70: Retur Penjualan Produk | C70: 4100 | D70: Pendapatan Operasional Utama | E70: Income | F70: 0 | G70: Income Account | H70: Retur Penjualan | I70: Pengurang pendapatan akibat pengembalian barang cacat
A71: 4140 | B71: Diskon & Potongan Penjualan | C71: 4100 | D71: Pendapatan Operasional Utama | E71: Income | F71: 0 | G71: Income Account | H71: Diskon Penjualan | I71: Potongan harga penjualan ke distributor/pelanggan
A72: 4200 | B72: Pendapatan Non-Operasional & Scrap | C72: 4000 | D72: PENDAPATAN | E72: Income | F72: 1 | G72: Income Account | H72: Pendapatan Lain-lain | I72: Hasil penjualan limbah/scrap & non-operasional
A73: 4210 | B73: Penjualan Limbah & Scrap Produksi | C73: 4200 | D73: Pendapatan Non-Operasional & Scrap | E73: Income | F73: 0 | G73: Income Account | H73: Penjualan Scrap | I73: Hasil penjualan sisa gram besi, plastik, potongan bahan
A74: 4220 | B74: Pendapatan Bunga Bank & Selisih Kurs | C74: 4200 | D74: Pendapatan Non-Operasional & Scrap | E74: Income | F74: 0 | G74: Income Account | H74: Pendapatan Bunga/Kurs | I74: Bunga tabungan/deposito & keuntungan selisih kurs valas
A75: 5000 | B75: HARGA POKOK PENJUALAN & BIAYA PRODUKSI | E75: Expense | F75: 1 | G75: Cost of Goods Sold | H75: Header Utama | I75: Induk utama biaya produksi & HPP manufaktur
A76: 5100 | B76: Harga Pokok Penjualan (COGS) | C76: 5000 | D76: HARGA POKOK PENJUALAN & BIAYA PRODUKSI | E76: Expense | F76: 1 | G76: Cost of Goods Sold | H76: HPP Terjual | I76: Nilai pokok barang yang terkirim ke pelanggan
A77: 5110 | B77: HPP Barang Jadi Terjual (COGS Finished Goods) | C77: 5100 | D77: Harga Pokok Penjualan (COGS) | E77: Expense | F77: 0 | G77: Cost of Goods Sold | H77: HPP Barang Jadi | I77: Terpotong otomatis saat Delivery Note / Sales Invoice
A78: 5120 | B78: HPP Penjualan Scrap / Limbah | C78: 5100 | D78: Harga Pokok Penjualan (COGS) | E78: Expense | F78: 0 | G78: Cost of Goods Sold | H78: HPP Scrap | I78: Nilai buku persediaan limbah yang terjual
A79: 5200 | B79: Biaya Bahan Langsung (Direct Materials) | C79: 5000 | D79: HARGA POKOK PENJUALAN & BIAYA PRODUKSI | E79: Expense | F79: 1 | G79: Expense Account | H79: Biaya Bahan Langsung | I79: Biaya bahan baku utama yang terserap produksi
A80: 5210 | B80: Biaya Pemakaian Bahan Baku Utama | C80: 5200 | D80: Biaya Bahan Langsung (Direct Materials) | E80: Expense | F80: 0 | G80: Expense Account | H80: Pemakaian Bahan Baku | I80: Terpotong dari stok saat Work Order / Stock Entry Manufacture
A81: 5220 | B81: Biaya Pemakaian Bahan Penolong / Pembantu | C81: 5200 | D81: Biaya Bahan Langsung (Direct Materials) | E81: Expense | F81: 0 | G81: Expense Account | H81: Pemakaian Bahan Penolong | I81: Terpotong saat penggunaan bahan kimia/perekat/baut di pabrik
A82: 5230 | B82: Biaya Pengangkutan & Impor Bahan Baku (Freight In) | C82: 5200 | D82: Biaya Bahan Langsung (Direct Materials) | E82: Expense | F82: 0 | G82: Expense Account | H82: Biaya Angkut Impor | I82: Biaya kontainer, impor, & ongkir bahan baku (Landed Cost)
A83: 5300 | B83: Biaya Tenaga Kerja Langsung (Direct Labor) | C83: 5000 | D83: HARGA POKOK PENJUALAN & BIAYA PRODUKSI | E83: Expense | F83: 1 | G83: Expense Account | H83: Tenaga Kerja Langsung | I83: Upah buruh yang bersentuhan langsung dengan mesin/produk
A84: 5310 | B84: Upah Buruh Pokok Produksi | C84: 5300 | D84: Biaya Tenaga Kerja Langsung (Direct Labor) | E84: Expense | F84: 0 | G84: Expense Account | H84: Upah Buruh Pabrik | I84: Gaji/upah borongan & harian buruh lini produksi
A85: 5320 | B85: Upah Lembur Buruh Pabrik | C85: 5300 | D85: Biaya Tenaga Kerja Langsung (Direct Labor) | E85: Expense | F85: 0 | G85: Expense Account | H85: Lembur Buruh | I85: Pembayaran jam lembur buruh produksi
A86: 5330 | B86: Tunjangan & BPJS Buruh Produksi | C86: 5300 | D86: Biaya Tenaga Kerja Langsung (Direct Labor) | E86: Expense | F86: 0 | G86: Expense Account | H86: Tunjangan Buruh | I86: BPJS Ketenagakerjaan & THR buruh pabrik
A87: 5400 | B87: Biaya Overhead Pabrik (Manufacturing Overhead - BOP) | C87: 5000 | D87: HARGA POKOK PENJUALAN & BIAYA PRODUKSI | E87: Expense | F87: 1 | G87: Expense Account | H87: Overhead Pabrik (BOP) | I87: Biaya tidak langsung untuk pengoperasian pabrik
... A96: 5490 | B96: Alokasi Overhead Pabrik (Overhead Absorbed) | C96: 5400 | D96: Biaya Overhead Pabrik (Manufacturing Overhead - BOP) | E96: Expense | F96: 0 | G96: Expense Account | H96: Alokasi BOP | I96: Akun penyeimbang alokasi BOP ke nilai HPP produk
A97: 6000 | B97: BEBAN OPERASIONAL (OPERATING EXPENSES) | E97: Expense | F97: 1 | G97: Expense Account | H97: Header Utama | I97: Induk beban non-produksi (pemasaran & umum)
A98: 6100 | B98: Beban Penjualan & Pemasaran | C98: 6000 | D98: BEBAN OPERASIONAL (OPERATING EXPENSES) | E98: Expense | F98: 1 | G98: Expense Account | H98: Beban Pemasaran | I98: Beban distribusi & komersial produk
A99: 6110 | B99: Biaya Pengiriman Barang Jadi ke Pelanggan (Freight Out) | C99: 6100 | D99: Beban Penjualan & Pemasaran | E99: Expense | F99: 0 | G99: Expense Account | H99: Ongkir Penjualan | I99: Biaya ekpedisi, truk, & kontainer pengiriman produk
A100: 6120 | B100: Gaji & Komisi Sales / Marketing | C100: 6100 | D100: Beban Penjualan & Pemasaran | E100: Expense | F100: 0 | G100: Expense Account | H100: Gaji Tim Sales | I100: Gaji pokok, bonus, & komisi tim penjualan
A101: 6130 | B101: Biaya Iklan, Pameran Industri & Promosi | C101: 6100 | D101: Beban Penjualan & Pemasaran | E101: Expense | F101: 0 | G101: Expense Account | H101: Promosi & Pameran | I101: Sewa booth pameran industri, brosur, & pemasaran digital
A102: 6140 | B102: Biaya Garansi, Retur & Klaim Kualitas | C102: 6100 | D102: Beban Penjualan & Pemasaran | E102: Expense | F102: 0 | G102: Expense Account | H102: Garansi & Klaim | I102: Biaya penggantian/perbaikan produk garansi pelanggan
A103: 6200 | B103: Beban Umum & Administrasi | C103: 6000 | D103: BEBAN OPERASIONAL (OPERATING EXPENSES) | E103: Expense | F103: 1 | G103: Expense Account | H103: Beban Umum & Admin | I103: Beban manajerial & operasional kantor pusat
A104: 6210 | B104: Gaji Direksi & Staf Administrasi Kantor | C104: 6200 | D104: Beban Umum & Administrasi | E104: Expense | F104: 0 | G104: Expense Account | H104: Gaji Admin & Direksi | I104: Gaji manajemen puncak, HRD, Finance, & IT kantor
A105: 6220 | B105: Sewa Kantor, Listrik, Air & Internet Kantor | C105: 6200 | D105: Beban Umum & Administrasi | E105: Expense | F105: 0 | G105: Expense Account | H105: Utilitas Kantor | I105: Biaya operasional kantor non-pabrik
A106: 6230 | B106: Biaya Alat Tulis Kantor (ATK) & Cetakan | C106: 6200 | D106: Beban Umum & Administrasi | E106: Expense | F106: 0 | G106: Expense Account | H106: Perlengkapan Kantor | I106: Pembelian kertas, tinta, & kebutuhan kantor
A107: 6240 | B107: Penyusutan Aset Tetap Kantor & IT | C107: 6200 | D107: Beban Umum & Administrasi | E107: Expense | F107: 0 | G107: Depreciation | H107: Depresiasi Kantor | I107: Beban penyusutan komputer, server, & inventaris kantor
A108: 6250 | B108: Biaya Perizinan, Legal, ISO & Konsultan | C108: 6200 | D108: Beban Umum & Administrasi | E108: Expense | F108: 0 | G108: Expense Account | H108: Legal & Sertifikasi | I108: Sertifikasi ISO, AMDAL, auditor akuntan, & konsultan
A109: 6260 | B109: Biaya Admin Bank, Pajak Bunga & Provisi | C109: 6200 | D109: Beban Umum & Administrasi | E109: Expense | F109: 0 | G109: Expense Account | H109: Admin Bank | I109: Biaya administrasi bulanan bank & provisi pinjaman
A110: 6270 | B110: Beban Kerugian Selisih Kurs Mata Uang | C110: 6200 | D110: Beban Umum & Administrasi | E110: Expense | F110: 0 | G110: Expense Account | H110: Rugi Selisih Kurs | I110: Kerugian akibat fluktuasi nilai tukar impor/ekspor

Sheet Petunjuk Import ERPNext
A1: PANDUAN IMPOR BAGAN AKUN KE ERPNEXT
A2: Langkah-langkah Praktis Mengunggah File ke Sistem ERPNext
A4: Langkah 1: Persiapan Perusahaan (Company)
A5: 1. Pastikan Perusahaan (Company) Anda sudah dibuat di ERPNext (Setup > Company).
A6: 2. Jika membuat Perusahaan baru, Anda bisa memilih opsi 'Chart of Accounts Importer' agar struktur bawaan kosong/bersih.
A8: Langkah 2: Menggunakan Chart of Accounts Importer di ERPNext
A9: 1. Masuk ke modul Accounting > Chart of Accounts Importer.
A10: 2. Pilih nama Perusahaan Anda pada kolom Company.
A11: 3. Ekspor/Simpan Tab 'Chart of Accounts ERPNext' dari file Excel ini menjadi format .CSV atau langsung Upload file .XLSX ini.
A12: 4. Petakan (Map) kolom Excel ke field ERPNext berikut:
A13: - Account Code -> Account Number / Code
A14: - Account Name -> Account Name
... A32: 5. Set Default Operating Cost Account = 5400 (Biaya Overhead Pabrik).

Sheet Ringkasan Struktur Akun
A1: RINGKASAN REKAPITULASI KODE AKUN MANUFAKTUR
A2: Distribusi Kelompok Akun dan Statistik Pemetaan ERPNext
A4: Kode Head | B4: Kategori Utama (Root Type) | C4: Jumlah Akun Induk (Group) | D4: Jumlah Akun Transaksi (Ledger) | E4: Total Akun | F4: Fokus Utama Manufaktur
A5: 1000 | B5: ASET (Assets) | C5: =COUNTIFS('Chart of Accounts ERPNext'!E5:E100, "Asset", 'Chart of Accounts ERPNext'!F5:F100, 1) | D5: =COUNTIFS('Chart of Accounts ERPNext'!E5:E100, "Asset", 'Chart of Accounts ERPNext'!F5:F100, 0) | E5: =SUM(C5:D5) | F5: Bahan Baku, WIP, Barang Jadi, Spareparts & Mesin Produksi
A6: 2000 | B6: KEWAJIBAN (Liabilities) | C6: =COUNTIFS('Chart of Accounts ERPNext'!E5:E100, "Liability", 'Chart of Accounts ERPNext'!F5:F100, 1) | D6: =COUNTIFS('Chart of Accounts ERPNext'!E5:E100, "Liability", 'Chart of Accounts ERPNext'!F5:F100, 0) | E6: =SUM(C6:D6) | F6: Hutang Supplier Bahan Baku, Makloon & Akrual Buruh
A7: 3000 | B7: EKUITAS (Equity) | C7: =COUNTIFS('Chart of Accounts ERPNext'!E5:E100, "Equity", 'Chart of Accounts ERPNext'!F5:F100, 1) | D7: =COUNTIFS('Chart of Accounts ERPNext'!E5:E100, "Equity", 'Chart of Accounts ERPNext'!F5:F100, 0) | E7: =SUM(C7:D7) | F7: Modal Disetor, Laba Ditahan & Clearing Adjust Stok
A8: 4000 | B8: PENDAPATAN (Income) | C8: =COUNTIFS('Chart of Accounts ERPNext'!E5:E100, "Income", 'Chart of Accounts ERPNext'!F5:F100, 1) | D8: =COUNTIFS('Chart of Accounts ERPNext'!E5:E100, "Income", 'Chart of Accounts ERPNext'!F5:F100, 0) | E8: =SUM(C8:D8) | F8: Penjualan Produk Manufaktur, Jasa Makloon & Scrap
A9: 5000 | B9: HPP & BIAYA PRODUKSI (Expense) | C9: =COUNTIFS('Chart of Accounts ERPNext'!E5:E100, "Expense", 'Chart of Accounts ERPNext'!A5:A100, "5*", 'Chart of Accounts ERPNext'!F5:F100, 1) | D9: =COUNTIFS('Chart of Accounts ERPNext'!E5:E100, "Expense", 'Chart of Accounts ERPNext'!A5:A100, "5*", 'Chart of Accounts ERPNext'!F5:F100, 0) | E9: =SUM(C9:D9) | F9: Biaya Bahan Langsung, Upah Buruh & Overhead Pabrik (BOP)
A10: 6000 | B10: BEBAN OPERASIONAL (Expense) | C10: =COUNTIFS('Chart of Accounts ERPNext'!E5:E100, "Expense", 'Chart of Accounts ERPNext'!A5:A100, "6*", 'Chart of Accounts ERPNext'!F5:F100, 1) | D10: =COUNTIFS('Chart of Accounts ERPNext'!E5:E100, "Expense", 'Chart of Accounts ERPNext'!A5:A100, "6*", 'Chart of Accounts ERPNext'!F5:F100, 0) | E10: =SUM(C10:D10) | F10: Beban Pengiriman (Freight Out), Sales & Umum Admin
B11: TOTAL KELOMPOK AKUN | C11: =SUM(C5:C10) | D11: =SUM(D5:D10) | E11: =SUM(E5:E10) | F11: Struktur Lengkap Kompatibel dengan ERPNext v14/v15/v16
